trio_amqp/__init__.py
trio_amqp/_version.py
trio_amqp/channel.py
trio_amqp/constants.py
trio_amqp/envelope.py
trio_amqp/exceptions.py
trio_amqp/frame.py
trio_amqp/future.py
trio_amqp/properties.py
trio_amqp/protocol.py
trio_amqp-0.2.8.dist-info/METADATA
trio_amqp-0.2.8.dist-info/RECORD
trio_amqp-0.2.8.dist-info/WHEEL
trio_amqp-0.2.8.dist-info/top_level.txt
