Metadata-Version: 2.1
Name: trio-amqp
Version: 0.2.8
Summary: AMQP implementation using trio
Home-page: https://github.com/python-trio/trio-amqp
Author: Matthias Urlichs
Author-email: matthias@urlichs.de
License: BSD
Download-URL: https://pypi.python.org/pypi/trio_amqp
Platform: all
Classifier: Development Status :: 4 - Beta
Classifier: Intended Audience :: Developers
Classifier: License :: OSI Approved :: BSD License
Classifier: Operating System :: OS Independent
Classifier: Programming Language :: Python
Classifier: Programming Language :: Python :: 3
Classifier: Programming Language :: Python :: 3.5
Classifier: Programming Language :: Python :: 3.6
Classifier: Programming Language :: Python :: 3.7
Classifier: Framework :: Trio
Requires-Dist: trio
